bohancompliment/__init__.py
bohancompliment/generator.py
bohancompliment-0.2.0.dist-info/LICENSE
bohancompliment-0.2.0.dist-info/METADATA
bohancompliment-0.2.0.dist-info/WHEEL
bohancompliment-0.2.0.dist-info/top_level.txt
bohancompliment-0.2.0.dist-info/RECORD
