Metadata-Version: 2.1
Name: bohancompliment
Version: 0.2.0
Summary: A fun package that generates compliments.
Home-page: https://github.com/software-students-fall2024/3-python-package-bogosort-but-better-1
Author: Bohan Hou
Author-email: Bohan Hou <bh2422@nyu.edu>
License: GNU GENERAL PUBLIC LICENSE
Project-URL: Homepage, https://github.com/software-students-fall2024/3-python-package-bogosort-but-better-1
Classifier: Programming Language :: Python :: 3
Classifier: Operating System :: OS Independent
Requires-Python: >=3.6
License-File: LICENSE
